twitter_email_hunter
main
