Metadata-Version: 1.1
Name: twitter-email-hunter
Version: 1.1.0
Summary: Search for email addresses in a twitter timeline
Home-page: http://github.com/rmotr_com/twitter-email-hunter
Author: Santiago Basulto
Author-email: santiago@rmotr.com
License: MIT
Download-URL: http://github.com/rmotr_com/twitter-email-hunter/tarball/1.1.0
Platform: UNKNOWN
